{
  "item": [
    {
      "id": "351b2d9e-e2d5-4581-8cc6-29b997b7002d",
      "name": "Calls",
      "description": {
        "content": "",
        "type": "text/plain"
      },
      "item": [
        {
          "id": "478e8489-0117-4a89-8284-ac443cc9d27c",
          "name": "Initiate outbound call",
          "request": {
            "name": "Initiate outbound call",
            "description": {},
            "url": {
              "path": [
                "call"
              ],
              "host": [
                "{{baseUrl}}"
              ],
              "query": [],
              "variable": []
            },
            "method": "POST",
            "auth": null
          },
          "response": [
            {
              "id": "26b4d935-8d72-454b-a40c-8f80f4c5a2c1",
              "name": "Call initiated",
              "originalRequest": {
                "url": {
                  "path": [
                    "call"
                  ],
                  "host": [
                    "{{baseUrl}}"
                  ],
                  "query": [],
                  "variable": []
                },
                "header": [
                  {
                    "description": {
                      "content": "Added as a part of security scheme: bearer",
                      "type": "text/plain"
                    },
                    "key": "Authorization",
                    "value": "Bearer <token>"
                  }
                ],
                "method": "POST",
                "body": {}
              },
              "status": "OK",
              "code": 200,
              "header": [
                {
                  "key": "Content-Type",
                  "value": "text/plain"
                }
              ],
              "body": "",
              "cookie": [],
              "_postman_previewlanguage": "text"
            }
          ],
          "event": [],
          "protocolProfileBehavior": {
            "disableBodyPruning": true
          }
        },
        {
          "id": "0281ee7c-f94b-44b8-925b-c3da9a2ecb7b",
          "name": "Get call status / info",
          "request": {
            "name": "Get call status / info",
            "description": {},
            "url": {
              "path": [
                "call",
                ":id"
              ],
              "host": [
                "{{baseUrl}}"
              ],
              "query": [],
              "variable": [
                {
                  "disabled": false,
                  "type": "any",
                  "value": "<string>",
                  "key": "id",
                  "description": "(Required) "
                }
              ]
            },
            "method": "GET",
            "auth": null
          },
          "response": [
            {
              "id": "0e4c3287-4359-43e1-99d3-9aa7c592815f",
              "name": "Call details",
              "originalRequest": {
                "url": {
                  "path": [
                    "call",
                    ":id"
                  ],
                  "host": [
                    "{{baseUrl}}"
                  ],
                  "query": [],
                  "variable": [
                    {
                      "disabled": false,
                      "type": "any",
                      "value": "<string>",
                      "key": "id",
                      "description": "(Required) "
                    }
                  ]
                },
                "header": [
                  {
                    "description": {
                      "content": "Added as a part of security scheme: bearer",
                      "type": "text/plain"
                    },
                    "key": "Authorization",
                    "value": "Bearer <token>"
                  }
                ],
                "method": "GET",
                "body": {}
              },
              "status": "OK",
              "code": 200,
              "header": [
                {
                  "key": "Content-Type",
                  "value": "text/plain"
                }
              ],
              "body": "",
              "cookie": [],
              "_postman_previewlanguage": "text"
            }
          ],
          "event": [],
          "protocolProfileBehavior": {
            "disableBodyPruning": true
          }
        },
        {
          "id": "e5b12ea2-9e25-4007-af6b-e76276b58387",
          "name": "List concluded calls",
          "request": {
            "name": "List concluded calls",
            "description": {},
            "url": {
              "path": [
                "calls"
              ],
              "host": [
                "{{baseUrl}}"
              ],
              "query": [],
              "variable": []
            },
            "method": "GET",
            "auth": null
          },
          "response": [
            {
              "id": "6fcb5a2e-4411-4576-b37f-85a627eb1552",
              "name": "List of calls",
              "originalRequest": {
                "url": {
                  "path": [
                    "calls"
                  ],
                  "host": [
                    "{{baseUrl}}"
                  ],
                  "query": [],
                  "variable": []
                },
                "header": [
                  {
                    "description": {
                      "content": "Added as a part of security scheme: bearer",
                      "type": "text/plain"
                    },
                    "key": "Authorization",
                    "value": "Bearer <token>"
                  }
                ],
                "method": "GET",
                "body": {}
              },
              "status": "OK",
              "code": 200,
              "header": [
                {
                  "key": "Content-Type",
                  "value": "text/plain"
                }
              ],
              "body": "",
              "cookie": [],
              "_postman_previewlanguage": "text"
            }
          ],
          "event": [],
          "protocolProfileBehavior": {
            "disableBodyPruning": true
          }
        },
        {
          "id": "45b5b505-090c-4fb1-9bb2-2d6da2ce60ce",
          "name": "Transfer active call",
          "request": {
            "name": "Transfer active call",
            "description": {},
            "url": {
              "path": [
                "call",
                ":id",
                "transfer"
              ],
              "host": [
                "{{baseUrl}}"
              ],
              "query": [],
              "variable": [
                {
                  "disabled": false,
                  "type": "any",
                  "value": "<string>",
                  "key": "id",
                  "description": "(Required) "
                }
              ]
            },
            "method": "POST",
            "auth": null
          },
          "response": [
            {
              "id": "21346776-3bb2-46ff-86af-5cbfa27d15bf",
              "name": "Call transferred",
              "originalRequest": {
                "url": {
                  "path": [
                    "call",
                    ":id",
                    "transfer"
                  ],
                  "host": [
                    "{{baseUrl}}"
                  ],
                  "query": [],
                  "variable": [
                    {
                      "disabled": false,
                      "type": "any",
                      "value": "<string>",
                      "key": "id",
                      "description": "(Required) "
                    }
                  ]
                },
                "header": [
                  {
                    "description": {
                      "content": "Added as a part of security scheme: bearer",
                      "type": "text/plain"
                    },
                    "key": "Authorization",
                    "value": "Bearer <token>"
                  }
                ],
                "method": "POST",
                "body": {}
              },
              "status": "OK",
              "code": 200,
              "header": [
                {
                  "key": "Content-Type",
                  "value": "text/plain"
                }
              ],
              "body": "",
              "cookie": [],
              "_postman_previewlanguage": "text"
            }
          ],
          "event": [],
          "protocolProfileBehavior": {
            "disableBodyPruning": true
          }
        },
        {
          "id": "2844d4c7-c5b6-4db1-b2db-d514d691e55f",
          "name": "Terminate call",
          "request": {
            "name": "Terminate call",
            "description": {},
            "url": {
              "path": [
                "call",
                ":id",
                "hangup"
              ],
              "host": [
                "{{baseUrl}}"
              ],
              "query": [],
              "variable": [
                {
                  "disabled": false,
                  "type": "any",
                  "value": "<string>",
                  "key": "id",
                  "description": "(Required) "
                }
              ]
            },
            "method": "POST",
            "auth": null
          },
          "response": [
            {
              "id": "dc26d9a7-2c94-4192-ae9e-cdef594e2995",
              "name": "Call ended",
              "originalRequest": {
                "url": {
                  "path": [
                    "call",
                    ":id",
                    "hangup"
                  ],
                  "host": [
                    "{{baseUrl}}"
                  ],
                  "query": [],
                  "variable": [
                    {
                      "disabled": false,
                      "type": "any",
                      "value": "<string>",
                      "key": "id",
                      "description": "(Required) "
                    }
                  ]
                },
                "header": [
                  {
                    "description": {
                      "content": "Added as a part of security scheme: bearer",
                      "type": "text/plain"
                    },
                    "key": "Authorization",
                    "value": "Bearer <token>"
                  }
                ],
                "method": "POST",
                "body": {}
              },
              "status": "OK",
              "code": 200,
              "header": [
                {
                  "key": "Content-Type",
                  "value": "text/plain"
                }
              ],
              "body": "",
              "cookie": [],
              "_postman_previewlanguage": "text"
            }
          ],
          "event": [],
          "protocolProfileBehavior": {
            "disableBodyPruning": true
          }
        },
        {
          "id": "980e9e8e-3ede-4377-a0a2-1845e94c7034",
          "name": "Add participants to call",
          "request": {
            "name": "Add participants to call",
            "description": {},
            "url": {
              "path": [
                "call",
                ":id",
                "participants"
              ],
              "host": [
                "{{baseUrl}}"
              ],
              "query": [],
              "variable": [
                {
                  "disabled": false,
                  "type": "any",
                  "value": "<string>",
                  "key": "id",
                  "description": "(Required) "
                }
              ]
            },
            "method": "POST",
            "auth": null
          },
          "response": [
            {
              "id": "1bf9efad-f998-4bbc-a43e-525b0f2c75aa",
              "name": "Participants added",
              "originalRequest": {
                "url": {
                  "path": [
                    "call",
                    ":id",
                    "participants"
                  ],
                  "host": [
                    "{{baseUrl}}"
                  ],
                  "query": [],
                  "variable": [
                    {
                      "disabled": false,
                      "type": "any",
                      "value": "<string>",
                      "key": "id",
                      "description": "(Required) "
                    }
                  ]
                },
                "header": [
                  {
                    "description": {
                      "content": "Added as a part of security scheme: bearer",
                      "type": "text/plain"
                    },
                    "key": "Authorization",
                    "value": "Bearer <token>"
                  }
                ],
                "method": "POST",
                "body": {}
              },
              "status": "OK",
              "code": 200,
              "header": [
                {
                  "key": "Content-Type",
                  "value": "text/plain"
                }
              ],
              "body": "",
              "cookie": [],
              "_postman_previewlanguage": "text"
            }
          ],
          "event": [],
          "protocolProfileBehavior": {
            "disableBodyPruning": true
          }
        },
        {
          "id": "7e666e60-07f4-4ceb-9d37-ffd48dc18579",
          "name": "Set call labels",
          "request": {
            "name": "Set call labels",
            "description": {},
            "url": {
              "path": [
                "call",
                ":id",
                "labels"
              ],
              "host": [
                "{{baseUrl}}"
              ],
              "query": [],
              "variable": [
                {
                  "disabled": false,
                  "type": "any",
                  "value": "<string>",
                  "key": "id",
                  "description": "(Required) "
                }
              ]
            },
            "method": "POST",
            "auth": null
          },
          "response": [
            {
              "id": "10c1fdb5-1f2c-47f2-a257-56a73ef4cb42",
              "name": "Labels updated",
              "originalRequest": {
                "url": {
                  "path": [
                    "call",
                    ":id",
                    "labels"
                  ],
                  "host": [
                    "{{baseUrl}}"
                  ],
                  "query": [],
                  "variable": [
                    {
                      "disabled": false,
                      "type": "any",
                      "value": "<string>",
                      "key": "id",
                      "description": "(Required) "
                    }
                  ]
                },
                "header": [
                  {
                    "description": {
                      "content": "Added as a part of security scheme: bearer",
                      "type": "text/plain"
                    },
                    "key": "Authorization",
                    "value": "Bearer <token>"
                  }
                ],
                "method": "POST",
                "body": {}
              },
              "status": "OK",
              "code": 200,
              "header": [
                {
                  "key": "Content-Type",
                  "value": "text/plain"
                }
              ],
              "body": "",
              "cookie": [],
              "_postman_previewlanguage": "text"
            }
          ],
          "event": [],
          "protocolProfileBehavior": {
            "disableBodyPruning": true
          }
        }
      ],
      "event": []
    },
    {
      "id": "39dc993f-f236-415b-9c3c-96a416cfa56f",
      "name": "Users",
      "description": {
        "content": "",
        "type": "text/plain"
      },
      "item": [
        {
          "id": "f5c1fcf2-9df7-45d2-9e7a-8193eaa452e7",
          "name": "List company users",
          "request": {
            "name": "List company users",
            "description": {},
            "url": {
              "path": [
                "users"
              ],
              "host": [
                "{{baseUrl}}"
              ],
              "query": [],
              "variable": []
            },
            "method": "GET",
            "auth": null
          },
          "response": [
            {
              "id": "a1ecaba0-8176-48e6-a9d3-67226463b663",
              "name": "Users",
              "originalRequest": {
                "url": {
                  "path": [
                    "users"
                  ],
                  "host": [
                    "{{baseUrl}}"
                  ],
                  "query": [],
                  "variable": []
                },
                "header": [
                  {
                    "description": {
                      "content": "Added as a part of security scheme: bearer",
                      "type": "text/plain"
                    },
                    "key": "Authorization",
                    "value": "Bearer <token>"
                  }
                ],
                "method": "GET",
                "body": {}
              },
              "status": "OK",
              "code": 200,
              "header": [
                {
                  "key": "Content-Type",
                  "value": "text/plain"
                }
              ],
              "body": "",
              "cookie": [],
              "_postman_previewlanguage": "text"
            }
          ],
          "event": [],
          "protocolProfileBehavior": {
            "disableBodyPruning": true
          }
        },
        {
          "id": "281be81d-8324-46de-8f29-14e4abf62fe8",
          "name": "Create user",
          "request": {
            "name": "Create user",
            "description": {},
            "url": {
              "path": [
                "users"
              ],
              "host": [
                "{{baseUrl}}"
              ],
              "query": [],
              "variable": []
            },
            "method": "POST",
            "auth": null
          },
          "response": [
            {
              "id": "44accd96-d34c-4c49-8fe2-4a9e3b20f097",
              "name": "User created",
              "originalRequest": {
                "url": {
                  "path": [
                    "users"
                  ],
                  "host": [
                    "{{baseUrl}}"
                  ],
                  "query": [],
                  "variable": []
                },
                "header": [
                  {
                    "description": {
                      "content": "Added as a part of security scheme: bearer",
                      "type": "text/plain"
                    },
                    "key": "Authorization",
                    "value": "Bearer <token>"
                  }
                ],
                "method": "POST",
                "body": {}
              },
              "status": "OK",
              "code": 200,
              "header": [
                {
                  "key": "Content-Type",
                  "value": "text/plain"
                }
              ],
              "body": "",
              "cookie": [],
              "_postman_previewlanguage": "text"
            }
          ],
          "event": [],
          "protocolProfileBehavior": {
            "disableBodyPruning": true
          }
        },
        {
          "id": "93f6983b-d61e-4621-becf-d0c0e4a8e1fe",
          "name": "Get user",
          "request": {
            "name": "Get user",
            "description": {},
            "url": {
              "path": [
                "users",
                ":id"
              ],
              "host": [
                "{{baseUrl}}"
              ],
              "query": [],
              "variable": [
                {
                  "disabled": false,
                  "type": "any",
                  "value": "<string>",
                  "key": "id",
                  "description": "(Required) "
                }
              ]
            },
            "method": "GET",
            "auth": null
          },
          "response": [
            {
              "id": "e80ce359-4cd8-495c-a46c-790b24435a24",
              "name": "User",
              "originalRequest": {
                "url": {
                  "path": [
                    "users",
                    ":id"
                  ],
                  "host": [
                    "{{baseUrl}}"
                  ],
                  "query": [],
                  "variable": [
                    {
                      "disabled": false,
                      "type": "any",
                      "value": "<string>",
                      "key": "id",
                      "description": "(Required) "
                    }
                  ]
                },
                "header": [
                  {
                    "description": {
                      "content": "Added as a part of security scheme: bearer",
                      "type": "text/plain"
                    },
                    "key": "Authorization",
                    "value": "Bearer <token>"
                  }
                ],
                "method": "GET",
                "body": {}
              },
              "status": "OK",
              "code": 200,
              "header": [
                {
                  "key": "Content-Type",
                  "value": "text/plain"
                }
              ],
              "body": "",
              "cookie": [],
              "_postman_previewlanguage": "text"
            }
          ],
          "event": [],
          "protocolProfileBehavior": {
            "disableBodyPruning": true
          }
        },
        {
          "id": "97761856-ea5d-483e-aad5-74b11287bfa2",
          "name": "Update user",
          "request": {
            "name": "Update user",
            "description": {},
            "url": {
              "path": [
                "users",
                ":id"
              ],
              "host": [
                "{{baseUrl}}"
              ],
              "query": [],
              "variable": [
                {
                  "disabled": false,
                  "type": "any",
                  "value": "<string>",
                  "key": "id",
                  "description": "(Required) "
                }
              ]
            },
            "method": "PATCH",
            "auth": null
          },
          "response": [
            {
              "id": "4bd35ddd-1274-432e-9bfe-2d03c31ded3b",
              "name": "User updated",
              "originalRequest": {
                "url": {
                  "path": [
                    "users",
                    ":id"
                  ],
                  "host": [
                    "{{baseUrl}}"
                  ],
                  "query": [],
                  "variable": [
                    {
                      "disabled": false,
                      "type": "any",
                      "value": "<string>",
                      "key": "id",
                      "description": "(Required) "
                    }
                  ]
                },
                "header": [
                  {
                    "description": {
                      "content": "Added as a part of security scheme: bearer",
                      "type": "text/plain"
                    },
                    "key": "Authorization",
                    "value": "Bearer <token>"
                  }
                ],
                "method": "PATCH",
                "body": {}
              },
              "status": "OK",
              "code": 200,
              "header": [
                {
                  "key": "Content-Type",
                  "value": "text/plain"
                }
              ],
              "body": "",
              "cookie": [],
              "_postman_previewlanguage": "text"
            }
          ],
          "event": [],
          "protocolProfileBehavior": {
            "disableBodyPruning": true
          }
        },
        {
          "id": "c4637dd5-f0a1-42f1-b5fe-aecaaa60ed54",
          "name": "Delete user",
          "request": {
            "name": "Delete user",
            "description": {},
            "url": {
              "path": [
                "users",
                ":id"
              ],
              "host": [
                "{{baseUrl}}"
              ],
              "query": [],
              "variable": [
                {
                  "disabled": false,
                  "type": "any",
                  "value": "<string>",
                  "key": "id",
                  "description": "(Required) "
                }
              ]
            },
            "method": "DELETE",
            "auth": null
          },
          "response": [
            {
              "id": "6c74f5b2-4b0c-43cc-b200-98f160b12b46",
              "name": "Deleted",
              "originalRequest": {
                "url": {
                  "path": [
                    "users",
                    ":id"
                  ],
                  "host": [
                    "{{baseUrl}}"
                  ],
                  "query": [],
                  "variable": [
                    {
                      "disabled": false,
                      "type": "any",
                      "value": "<string>",
                      "key": "id",
                      "description": "(Required) "
                    }
                  ]
                },
                "header": [
                  {
                    "description": {
                      "content": "Added as a part of security scheme: bearer",
                      "type": "text/plain"
                    },
                    "key": "Authorization",
                    "value": "Bearer <token>"
                  }
                ],
                "method": "DELETE",
                "body": {}
              },
              "status": "No Content",
              "code": 204,
              "header": [
                {
                  "key": "Content-Type",
                  "value": "text/plain"
                }
              ],
              "body": "",
              "cookie": [],
              "_postman_previewlanguage": "text"
            }
          ],
          "event": [],
          "protocolProfileBehavior": {
            "disableBodyPruning": true
          }
        },
        {
          "id": "ddd7d01c-cc30-455a-a9e3-270c5ac9c843",
          "name": "Initiate call on behalf of user",
          "request": {
            "name": "Initiate call on behalf of user",
            "description": {},
            "url": {
              "path": [
                "users",
                ":id",
                "call"
              ],
              "host": [
                "{{baseUrl}}"
              ],
              "query": [],
              "variable": [
                {
                  "disabled": false,
                  "type": "any",
                  "value": "<string>",
                  "key": "id",
                  "description": "(Required) "
                }
              ]
            },
            "method": "POST",
            "auth": null
          },
          "response": [
            {
              "id": "bb5df93d-e55a-4dca-afd3-5af1638319a5",
              "name": "Call initiated",
              "originalRequest": {
                "url": {
                  "path": [
                    "users",
                    ":id",
                    "call"
                  ],
                  "host": [
                    "{{baseUrl}}"
                  ],
                  "query": [],
                  "variable": [
                    {
                      "disabled": false,
                      "type": "any",
                      "value": "<string>",
                      "key": "id",
                      "description": "(Required) "
                    }
                  ]
                },
                "header": [
                  {
                    "description": {
                      "content": "Added as a part of security scheme: bearer",
                      "type": "text/plain"
                    },
                    "key": "Authorization",
                    "value": "Bearer <token>"
                  }
                ],
                "method": "POST",
                "body": {}
              },
              "status": "OK",
              "code": 200,
              "header": [
                {
                  "key": "Content-Type",
                  "value": "text/plain"
                }
              ],
              "body": "",
              "cookie": [],
              "_postman_previewlanguage": "text"
            }
          ],
          "event": [],
          "protocolProfileBehavior": {
            "disableBodyPruning": true
          }
        }
      ],
      "event": []
    },
    {
      "id": "fc120d2d-e026-41e8-8453-0d28beacb105",
      "name": "Offices",
      "description": {
        "content": "",
        "type": "text/plain"
      },
      "item": [
        {
          "id": "a024ae85-4c62-45e8-b0a0-b2b13139738a",
          "name": "List offices",
          "request": {
            "name": "List offices",
            "description": {},
            "url": {
              "path": [
                "offices"
              ],
              "host": [
                "{{baseUrl}}"
              ],
              "query": [],
              "variable": []
            },
            "method": "GET",
            "auth": null
          },
          "response": [
            {
              "id": "9f900f42-7fb4-42cc-91a9-7a03efef2cfe",
              "name": "Offices",
              "originalRequest": {
                "url": {
                  "path": [
                    "offices"
                  ],
                  "host": [
                    "{{baseUrl}}"
                  ],
                  "query": [],
                  "variable": []
                },
                "header": [
                  {
                    "description": {
                      "content": "Added as a part of security scheme: bearer",
                      "type": "text/plain"
                    },
                    "key": "Authorization",
                    "value": "Bearer <token>"
                  }
                ],
                "method": "GET",
                "body": {}
              },
              "status": "OK",
              "code": 200,
              "header": [
                {
                  "key": "Content-Type",
                  "value": "text/plain"
                }
              ],
              "body": "",
              "cookie": [],
              "_postman_previewlanguage": "text"
            }
          ],
          "event": [],
          "protocolProfileBehavior": {
            "disableBodyPruning": true
          }
        },
        {
          "id": "db2532c8-8898-484c-af83-8e406c8bf2a0",
          "name": "Create secondary office",
          "request": {
            "name": "Create secondary office",
            "description": {},
            "url": {
              "path": [
                "offices"
              ],
              "host": [
                "{{baseUrl}}"
              ],
              "query": [],
              "variable": []
            },
            "method": "POST",
            "auth": null
          },
          "response": [
            {
              "id": "511c3df8-7324-41c5-b0c3-d7394096e014",
              "name": "Office created",
              "originalRequest": {
                "url": {
                  "path": [
                    "offices"
                  ],
                  "host": [
                    "{{baseUrl}}"
                  ],
                  "query": [],
                  "variable": []
                },
                "header": [
                  {
                    "description": {
                      "content": "Added as a part of security scheme: bearer",
                      "type": "text/plain"
                    },
                    "key": "Authorization",
                    "value": "Bearer <token>"
                  }
                ],
                "method": "POST",
                "body": {}
              },
              "status": "OK",
              "code": 200,
              "header": [
                {
                  "key": "Content-Type",
                  "value": "text/plain"
                }
              ],
              "body": "",
              "cookie": [],
              "_postman_previewlanguage": "text"
            }
          ],
          "event": [],
          "protocolProfileBehavior": {
            "disableBodyPruning": true
          }
        },
        {
          "id": "359f4c4e-f6ce-4fd4-8e85-5ccd286536ef",
          "name": "Get office",
          "request": {
            "name": "Get office",
            "description": {},
            "url": {
              "path": [
                "offices",
                ":id"
              ],
              "host": [
                "{{baseUrl}}"
              ],
              "query": [],
              "variable": [
                {
                  "disabled": false,
                  "type": "any",
                  "value": "<string>",
                  "key": "id",
                  "description": "(Required) "
                }
              ]
            },
            "method": "GET",
            "auth": null
          },
          "response": [
            {
              "id": "5fe8de08-5dfe-43a3-beda-12fb1432a946",
              "name": "Office",
              "originalRequest": {
                "url": {
                  "path": [
                    "offices",
                    ":id"
                  ],
                  "host": [
                    "{{baseUrl}}"
                  ],
                  "query": [],
                  "variable": [
                    {
                      "disabled": false,
                      "type": "any",
                      "value": "<string>",
                      "key": "id",
                      "description": "(Required) "
                    }
                  ]
                },
                "header": [
                  {
                    "description": {
                      "content": "Added as a part of security scheme: bearer",
                      "type": "text/plain"
                    },
                    "key": "Authorization",
                    "value": "Bearer <token>"
                  }
                ],
                "method": "GET",
                "body": {}
              },
              "status": "OK",
              "code": 200,
              "header": [
                {
                  "key": "Content-Type",
                  "value": "text/plain"
                }
              ],
              "body": "",
              "cookie": [],
              "_postman_previewlanguage": "text"
            }
          ],
          "event": [],
          "protocolProfileBehavior": {
            "disableBodyPruning": true
          }
        },
        {
          "id": "f0199042-04b6-4349-8aba-74001518216e",
          "name": "Update office",
          "request": {
            "name": "Update office",
            "description": {},
            "url": {
              "path": [
                "offices",
                ":id"
              ],
              "host": [
                "{{baseUrl}}"
              ],
              "query": [],
              "variable": [
                {
                  "disabled": false,
                  "type": "any",
                  "value": "<string>",
                  "key": "id",
                  "description": "(Required) "
                }
              ]
            },
            "method": "PATCH",
            "auth": null
          },
          "response": [
            {
              "id": "741a4e77-c0bf-4030-b0ce-0bc81fe56385",
              "name": "Office updated",
              "originalRequest": {
                "url": {
                  "path": [
                    "offices",
                    ":id"
                  ],
                  "host": [
                    "{{baseUrl}}"
                  ],
                  "query": [],
                  "variable": [
                    {
                      "disabled": false,
                      "type": "any",
                      "value": "<string>",
                      "key": "id",
                      "description": "(Required) "
                    }
                  ]
                },
                "header": [
                  {
                    "description": {
                      "content": "Added as a part of security scheme: bearer",
                      "type": "text/plain"
                    },
                    "key": "Authorization",
                    "value": "Bearer <token>"
                  }
                ],
                "method": "PATCH",
                "body": {}
              },
              "status": "OK",
              "code": 200,
              "header": [
                {
                  "key": "Content-Type",
                  "value": "text/plain"
                }
              ],
              "body": "",
              "cookie": [],
              "_postman_previewlanguage": "text"
            }
          ],
          "event": [],
          "protocolProfileBehavior": {
            "disableBodyPruning": true
          }
        }
      ],
      "event": []
    },
    {
      "id": "523d169c-444e-4613-a0ae-1121be47aaeb",
      "name": "Contacts",
      "description": {
        "content": "",
        "type": "text/plain"
      },
      "item": [
        {
          "id": "e1c50b6f-302f-47a2-a521-49ce21e516b7",
          "name": "List contacts",
          "request": {
            "name": "List contacts",
            "description": {},
            "url": {
              "path": [
                "contacts"
              ],
              "host": [
                "{{baseUrl}}"
              ],
              "query": [],
              "variable": []
            },
            "method": "GET",
            "auth": null
          },
          "response": [
            {
              "id": "7d0fa657-7bbd-4c0b-9b9a-27b4767435f9",
              "name": "Contacts",
              "originalRequest": {
                "url": {
                  "path": [
                    "contacts"
                  ],
                  "host": [
                    "{{baseUrl}}"
                  ],
                  "query": [],
                  "variable": []
                },
                "header": [
                  {
                    "description": {
                      "content": "Added as a part of security scheme: bearer",
                      "type": "text/plain"
                    },
                    "key": "Authorization",
                    "value": "Bearer <token>"
                  }
                ],
                "method": "GET",
                "body": {}
              },
              "status": "OK",
              "code": 200,
              "header": [
                {
                  "key": "Content-Type",
                  "value": "text/plain"
                }
              ],
              "body": "",
              "cookie": [],
              "_postman_previewlanguage": "text"
            }
          ],
          "event": [],
          "protocolProfileBehavior": {
            "disableBodyPruning": true
          }
        },
        {
          "id": "669185b4-833d-420c-9ec4-2d06ee18614d",
          "name": "Create contact",
          "request": {
            "name": "Create contact",
            "description": {},
            "url": {
              "path": [
                "contacts"
              ],
              "host": [
                "{{baseUrl}}"
              ],
              "query": [],
              "variable": []
            },
            "method": "POST",
            "auth": null
          },
          "response": [
            {
              "id": "f45de984-77c4-45a7-95d5-9e6b9ce336e8",
              "name": "Contact created",
              "originalRequest": {
                "url": {
                  "path": [
                    "contacts"
                  ],
                  "host": [
                    "{{baseUrl}}"
                  ],
                  "query": [],
                  "variable": []
                },
                "header": [
                  {
                    "description": {
                      "content": "Added as a part of security scheme: bearer",
                      "type": "text/plain"
                    },
                    "key": "Authorization",
                    "value": "Bearer <token>"
                  }
                ],
                "method": "POST",
                "body": {}
              },
              "status": "OK",
              "code": 200,
              "header": [
                {
                  "key": "Content-Type",
                  "value": "text/plain"
                }
              ],
              "body": "",
              "cookie": [],
              "_postman_previewlanguage": "text"
            }
          ],
          "event": [],
          "protocolProfileBehavior": {
            "disableBodyPruning": true
          }
        },
        {
          "id": "6c2f8a80-2d09-4d16-aa9e-1ae55688aed7",
          "name": "Get contact",
          "request": {
            "name": "Get contact",
            "description": {},
            "url": {
              "path": [
                "contacts",
                ":id"
              ],
              "host": [
                "{{baseUrl}}"
              ],
              "query": [],
              "variable": [
                {
                  "disabled": false,
                  "type": "any",
                  "value": "<string>",
                  "key": "id",
                  "description": "(Required) "
                }
              ]
            },
            "method": "GET",
            "auth": null
          },
          "response": [
            {
              "id": "22bd1e50-3747-496f-93d6-ab5cf377b370",
              "name": "Contact",
              "originalRequest": {
                "url": {
                  "path": [
                    "contacts",
                    ":id"
                  ],
                  "host": [
                    "{{baseUrl}}"
                  ],
                  "query": [],
                  "variable": [
                    {
                      "disabled": false,
                      "type": "any",
                      "value": "<string>",
                      "key": "id",
                      "description": "(Required) "
                    }
                  ]
                },
                "header": [
                  {
                    "description": {
                      "content": "Added as a part of security scheme: bearer",
                      "type": "text/plain"
                    },
                    "key": "Authorization",
                    "value": "Bearer <token>"
                  }
                ],
                "method": "GET",
                "body": {}
              },
              "status": "OK",
              "code": 200,
              "header": [
                {
                  "key": "Content-Type",
                  "value": "text/plain"
                }
              ],
              "body": "",
              "cookie": [],
              "_postman_previewlanguage": "text"
            }
          ],
          "event": [],
          "protocolProfileBehavior": {
            "disableBodyPruning": true
          }
        },
        {
          "id": "ac0a7d70-717c-4d59-bb58-d0aba94e1710",
          "name": "Update contact",
          "request": {
            "name": "Update contact",
            "description": {},
            "url": {
              "path": [
                "contacts",
                ":id"
              ],
              "host": [
                "{{baseUrl}}"
              ],
              "query": [],
              "variable": [
                {
                  "disabled": false,
                  "type": "any",
                  "value": "<string>",
                  "key": "id",
                  "description": "(Required) "
                }
              ]
            },
            "method": "PATCH",
            "auth": null
          },
          "response": [
            {
              "id": "80ad2b2d-a036-43c5-bf9a-abb24ba7f638",
              "name": "Updated",
              "originalRequest": {
                "url": {
                  "path": [
                    "contacts",
                    ":id"
                  ],
                  "host": [
                    "{{baseUrl}}"
                  ],
                  "query": [],
                  "variable": [
                    {
                      "disabled": false,
                      "type": "any",
                      "value": "<string>",
                      "key": "id",
                      "description": "(Required) "
                    }
                  ]
                },
                "header": [
                  {
                    "description": {
                      "content": "Added as a part of security scheme: bearer",
                      "type": "text/plain"
                    },
                    "key": "Authorization",
                    "value": "Bearer <token>"
                  }
                ],
                "method": "PATCH",
                "body": {}
              },
              "status": "OK",
              "code": 200,
              "header": [
                {
                  "key": "Content-Type",
                  "value": "text/plain"
                }
              ],
              "body": "",
              "cookie": [],
              "_postman_previewlanguage": "text"
            }
          ],
          "event": [],
          "protocolProfileBehavior": {
            "disableBodyPruning": true
          }
        },
        {
          "id": "9d52b04e-43e1-42bf-9d63-8391bbefc8e6",
          "name": "Delete contact",
          "request": {
            "name": "Delete contact",
            "description": {},
            "url": {
              "path": [
                "contacts",
                ":id"
              ],
              "host": [
                "{{baseUrl}}"
              ],
              "query": [],
              "variable": [
                {
                  "disabled": false,
                  "type": "any",
                  "value": "<string>",
                  "key": "id",
                  "description": "(Required) "
                }
              ]
            },
            "method": "DELETE",
            "auth": null
          },
          "response": [
            {
              "id": "7b87fd1a-6ddb-405e-8d5d-42174781ebdd",
              "name": "Deleted",
              "originalRequest": {
                "url": {
                  "path": [
                    "contacts",
                    ":id"
                  ],
                  "host": [
                    "{{baseUrl}}"
                  ],
                  "query": [],
                  "variable": [
                    {
                      "disabled": false,
                      "type": "any",
                      "value": "<string>",
                      "key": "id",
                      "description": "(Required) "
                    }
                  ]
                },
                "header": [
                  {
                    "description": {
                      "content": "Added as a part of security scheme: bearer",
                      "type": "text/plain"
                    },
                    "key": "Authorization",
                    "value": "Bearer <token>"
                  }
                ],
                "method": "DELETE",
                "body": {}
              },
              "status": "No Content",
              "code": 204,
              "header": [
                {
                  "key": "Content-Type",
                  "value": "text/plain"
                }
              ],
              "body": "",
              "cookie": [],
              "_postman_previewlanguage": "text"
            }
          ],
          "event": [],
          "protocolProfileBehavior": {
            "disableBodyPruning": true
          }
        }
      ],
      "event": []
    },
    {
      "id": "0a85a928-87ce-4664-883d-57060179c30e",
      "name": "Rooms",
      "description": {
        "content": "",
        "type": "text/plain"
      },
      "item": [
        {
          "id": "a8bdd157-b6d8-4bb0-82ac-6ce5b9fcd62c",
          "name": "List rooms",
          "request": {
            "name": "List rooms",
            "description": {},
            "url": {
              "path": [
                "rooms"
              ],
              "host": [
                "{{baseUrl}}"
              ],
              "query": [],
              "variable": []
            },
            "method": "GET",
            "auth": null
          },
          "response": [
            {
              "id": "eeaddc2c-6b22-424d-b842-bacefd8c0dfa",
              "name": "Rooms",
              "originalRequest": {
                "url": {
                  "path": [
                    "rooms"
                  ],
                  "host": [
                    "{{baseUrl}}"
                  ],
                  "query": [],
                  "variable": []
                },
                "header": [
                  {
                    "description": {
                      "content": "Added as a part of security scheme: bearer",
                      "type": "text/plain"
                    },
                    "key": "Authorization",
                    "value": "Bearer <token>"
                  }
                ],
                "method": "GET",
                "body": {}
              },
              "status": "OK",
              "code": 200,
              "header": [
                {
                  "key": "Content-Type",
                  "value": "text/plain"
                }
              ],
              "body": "",
              "cookie": [],
              "_postman_previewlanguage": "text"
            }
          ],
          "event": [],
          "protocolProfileBehavior": {
            "disableBodyPruning": true
          }
        },
        {
          "id": "fea9966c-6feb-4300-a9b0-1b9b8fcaf8a6",
          "name": "Create room",
          "request": {
            "name": "Create room",
            "description": {},
            "url": {
              "path": [
                "rooms"
              ],
              "host": [
                "{{baseUrl}}"
              ],
              "query": [],
              "variable": []
            },
            "method": "POST",
            "auth": null
          },
          "response": [
            {
              "id": "a3465b26-994c-40e1-b6b8-f2cbfa4072a4",
              "name": "Room created",
              "originalRequest": {
                "url": {
                  "path": [
                    "rooms"
                  ],
                  "host": [
                    "{{baseUrl}}"
                  ],
                  "query": [],
                  "variable": []
                },
                "header": [
                  {
                    "description": {
                      "content": "Added as a part of security scheme: bearer",
                      "type": "text/plain"
                    },
                    "key": "Authorization",
                    "value": "Bearer <token>"
                  }
                ],
                "method": "POST",
                "body": {}
              },
              "status": "OK",
              "code": 200,
              "header": [
                {
                  "key": "Content-Type",
                  "value": "text/plain"
                }
              ],
              "body": "",
              "cookie": [],
              "_postman_previewlanguage": "text"
            }
          ],
          "event": [],
          "protocolProfileBehavior": {
            "disableBodyPruning": true
          }
        },
        {
          "id": "7a678511-7b4d-4c76-b5d9-3aa7571e8b76",
          "name": "Get room",
          "request": {
            "name": "Get room",
            "description": {},
            "url": {
              "path": [
                "rooms",
                ":id"
              ],
              "host": [
                "{{baseUrl}}"
              ],
              "query": [],
              "variable": [
                {
                  "disabled": false,
                  "type": "any",
                  "value": "<string>",
                  "key": "id",
                  "description": "(Required) "
                }
              ]
            },
            "method": "GET",
            "auth": null
          },
          "response": [
            {
              "id": "eff20e03-966a-444f-88ca-48ed053965c3",
              "name": "Room",
              "originalRequest": {
                "url": {
                  "path": [
                    "rooms",
                    ":id"
                  ],
                  "host": [
                    "{{baseUrl}}"
                  ],
                  "query": [],
                  "variable": [
                    {
                      "disabled": false,
                      "type": "any",
                      "value": "<string>",
                      "key": "id",
                      "description": "(Required) "
                    }
                  ]
                },
                "header": [
                  {
                    "description": {
                      "content": "Added as a part of security scheme: bearer",
                      "type": "text/plain"
                    },
                    "key": "Authorization",
                    "value": "Bearer <token>"
                  }
                ],
                "method": "GET",
                "body": {}
              },
              "status": "OK",
              "code": 200,
              "header": [
                {
                  "key": "Content-Type",
                  "value": "text/plain"
                }
              ],
              "body": "",
              "cookie": [],
              "_postman_previewlanguage": "text"
            }
          ],
          "event": [],
          "protocolProfileBehavior": {
            "disableBodyPruning": true
          }
        },
        {
          "id": "603fec45-b2e5-4ebb-a249-a38c19e4acd6",
          "name": "Update room",
          "request": {
            "name": "Update room",
            "description": {},
            "url": {
              "path": [
                "rooms",
                ":id"
              ],
              "host": [
                "{{baseUrl}}"
              ],
              "query": [],
              "variable": [
                {
                  "disabled": false,
                  "type": "any",
                  "value": "<string>",
                  "key": "id",
                  "description": "(Required) "
                }
              ]
            },
            "method": "PATCH",
            "auth": null
          },
          "response": [
            {
              "id": "07a653c2-619f-48d1-bcbf-01f0b105a9da",
              "name": "Updated",
              "originalRequest": {
                "url": {
                  "path": [
                    "rooms",
                    ":id"
                  ],
                  "host": [
                    "{{baseUrl}}"
                  ],
                  "query": [],
                  "variable": [
                    {
                      "disabled": false,
                      "type": "any",
                      "value": "<string>",
                      "key": "id",
                      "description": "(Required) "
                    }
                  ]
                },
                "header": [
                  {
                    "description": {
                      "content": "Added as a part of security scheme: bearer",
                      "type": "text/plain"
                    },
                    "key": "Authorization",
                    "value": "Bearer <token>"
                  }
                ],
                "method": "PATCH",
                "body": {}
              },
              "status": "OK",
              "code": 200,
              "header": [
                {
                  "key": "Content-Type",
                  "value": "text/plain"
                }
              ],
              "body": "",
              "cookie": [],
              "_postman_previewlanguage": "text"
            }
          ],
          "event": [],
          "protocolProfileBehavior": {
            "disableBodyPruning": true
          }
        }
      ],
      "event": []
    },
    {
      "id": "040dd83c-7001-4acc-b37f-108b640f86f8",
      "name": "Transcripts",
      "description": {
        "content": "",
        "type": "text/plain"
      },
      "item": [
        {
          "id": "80b941cd-dc99-4bf5-8fb0-7b3802029225",
          "name": "Get call transcript",
          "request": {
            "name": "Get call transcript",
            "description": {},
            "url": {
              "path": [
                "transcripts",
                ":call_id"
              ],
              "host": [
                "{{baseUrl}}"
              ],
              "query": [],
              "variable": [
                {
                  "disabled": false,
                  "type": "any",
                  "value": "<string>",
                  "key": "call_id",
                  "description": "(Required) "
                }
              ]
            },
            "method": "GET",
            "auth": null
          },
          "response": [
            {
              "id": "e616e110-6023-4900-9877-63b915eeb48a",
              "name": "Transcript",
              "originalRequest": {
                "url": {
                  "path": [
                    "transcripts",
                    ":call_id"
                  ],
                  "host": [
                    "{{baseUrl}}"
                  ],
                  "query": [],
                  "variable": [
                    {
                      "disabled": false,
                      "type": "any",
                      "value": "<string>",
                      "key": "call_id",
                      "description": "(Required) "
                    }
                  ]
                },
                "header": [
                  {
                    "description": {
                      "content": "Added as a part of security scheme: bearer",
                      "type": "text/plain"
                    },
                    "key": "Authorization",
                    "value": "Bearer <token>"
                  }
                ],
                "method": "GET",
                "body": {}
              },
              "status": "OK",
              "code": 200,
              "header": [
                {
                  "key": "Content-Type",
                  "value": "text/plain"
                }
              ],
              "body": "",
              "cookie": [],
              "_postman_previewlanguage": "text"
            }
          ],
          "event": [],
          "protocolProfileBehavior": {
            "disableBodyPruning": true
          }
        },
        {
          "id": "2e68087a-4800-4849-811b-552aec4d371b",
          "name": "Get transcript URL",
          "request": {
            "name": "Get transcript URL",
            "description": {},
            "url": {
              "path": [
                "transcripts",
                ":call_id",
                "url"
              ],
              "host": [
                "{{baseUrl}}"
              ],
              "query": [],
              "variable": [
                {
                  "disabled": false,
                  "type": "any",
                  "value": "<string>",
                  "key": "call_id",
                  "description": "(Required) "
                }
              ]
            },
            "method": "GET",
            "auth": null
          },
          "response": [
            {
              "id": "3d4ee939-ae5f-4b9e-93a4-8cb7236c58ad",
              "name": "URL",
              "originalRequest": {
                "url": {
                  "path": [
                    "transcripts",
                    ":call_id",
                    "url"
                  ],
                  "host": [
                    "{{baseUrl}}"
                  ],
                  "query": [],
                  "variable": [
                    {
                      "disabled": false,
                      "type": "any",
                      "value": "<string>",
                      "key": "call_id",
                      "description": "(Required) "
                    }
                  ]
                },
                "header": [
                  {
                    "description": {
                      "content": "Added as a part of security scheme: bearer",
                      "type": "text/plain"
                    },
                    "key": "Authorization",
                    "value": "Bearer <token>"
                  }
                ],
                "method": "GET",
                "body": {}
              },
              "status": "OK",
              "code": 200,
              "header": [
                {
                  "key": "Content-Type",
                  "value": "text/plain"
                }
              ],
              "body": "",
              "cookie": [],
              "_postman_previewlanguage": "text"
            }
          ],
          "event": [],
          "protocolProfileBehavior": {
            "disableBodyPruning": true
          }
        }
      ],
      "event": []
    },
    {
      "id": "af325580-517f-47ee-b41f-04cdf9bba1f8",
      "name": "Recordings",
      "description": {
        "content": "",
        "type": "text/plain"
      },
      "item": [
        {
          "id": "7d9035a2-f2d3-4feb-839e-e16042c9f210",
          "name": "Create recording share link",
          "request": {
            "name": "Create recording share link",
            "description": {},
            "url": {
              "path": [
                "recording_share_link"
              ],
              "host": [
                "{{baseUrl}}"
              ],
              "query": [],
              "variable": []
            },
            "method": "POST",
            "auth": null
          },
          "response": [
            {
              "id": "7c27db3a-0494-4275-b64c-9ae4dfcd3f17",
              "name": "Share link created",
              "originalRequest": {
                "url": {
                  "path": [
                    "recording_share_link"
                  ],
                  "host": [
                    "{{baseUrl}}"
                  ],
                  "query": [],
                  "variable": []
                },
                "header": [
                  {
                    "description": {
                      "content": "Added as a part of security scheme: bearer",
                      "type": "text/plain"
                    },
                    "key": "Authorization",
                    "value": "Bearer <token>"
                  }
                ],
                "method": "POST",
                "body": {}
              },
              "status": "OK",
              "code": 200,
              "header": [
                {
                  "key": "Content-Type",
                  "value": "text/plain"
                }
              ],
              "body": "",
              "cookie": [],
              "_postman_previewlanguage": "text"
            }
          ],
          "event": [],
          "protocolProfileBehavior": {
            "disableBodyPruning": true
          }
        },
        {
          "id": "eeaba6e6-e53b-421a-85c7-b55f71bf5f01",
          "name": "Get recording share link",
          "request": {
            "name": "Get recording share link",
            "description": {},
            "url": {
              "path": [
                "recording_share_link",
                ":id"
              ],
              "host": [
                "{{baseUrl}}"
              ],
              "query": [],
              "variable": [
                {
                  "disabled": false,
                  "type": "any",
                  "value": "<string>",
                  "key": "id",
                  "description": "(Required) "
                }
              ]
            },
            "method": "GET",
            "auth": null
          },
          "response": [
            {
              "id": "f799374c-d787-4a05-9f10-f33548ab3295",
              "name": "Share link",
              "originalRequest": {
                "url": {
                  "path": [
                    "recording_share_link",
                    ":id"
                  ],
                  "host": [
                    "{{baseUrl}}"
                  ],
                  "query": [],
                  "variable": [
                    {
                      "disabled": false,
                      "type": "any",
                      "value": "<string>",
                      "key": "id",
                      "description": "(Required) "
                    }
                  ]
                },
                "header": [
                  {
                    "description": {
                      "content": "Added as a part of security scheme: bearer",
                      "type": "text/plain"
                    },
                    "key": "Authorization",
                    "value": "Bearer <token>"
                  }
                ],
                "method": "GET",
                "body": {}
              },
              "status": "OK",
              "code": 200,
              "header": [
                {
                  "key": "Content-Type",
                  "value": "text/plain"
                }
              ],
              "body": "",
              "cookie": [],
              "_postman_previewlanguage": "text"
            }
          ],
          "event": [],
          "protocolProfileBehavior": {
            "disableBodyPruning": true
          }
        }
      ],
      "event": []
    },
    {
      "id": "ef15e2ae-fde8-4198-bd96-126452dcc82f",
      "name": "Webhooks",
      "description": {
        "content": "",
        "type": "text/plain"
      },
      "item": [
        {
          "id": "c53b975e-c043-4b43-a91a-1df54a91569b",
          "name": "List webhooks",
          "request": {
            "name": "List webhooks",
            "description": {},
            "url": {
              "path": [
                "webhooks"
              ],
              "host": [
                "{{baseUrl}}"
              ],
              "query": [],
              "variable": []
            },
            "method": "GET",
            "auth": null
          },
          "response": [
            {
              "id": "2be93fff-c4da-4895-a6a9-83b40608bce8",
              "name": "Webhooks",
              "originalRequest": {
                "url": {
                  "path": [
                    "webhooks"
                  ],
                  "host": [
                    "{{baseUrl}}"
                  ],
                  "query": [],
                  "variable": []
                },
                "header": [
                  {
                    "description": {
                      "content": "Added as a part of security scheme: bearer",
                      "type": "text/plain"
                    },
                    "key": "Authorization",
                    "value": "Bearer <token>"
                  }
                ],
                "method": "GET",
                "body": {}
              },
              "status": "OK",
              "code": 200,
              "header": [
                {
                  "key": "Content-Type",
                  "value": "text/plain"
                }
              ],
              "body": "",
              "cookie": [],
              "_postman_previewlanguage": "text"
            }
          ],
          "event": [],
          "protocolProfileBehavior": {
            "disableBodyPruning": true
          }
        },
        {
          "id": "90664175-5e30-4dcf-b794-1a8e8226c139",
          "name": "Create webhook",
          "request": {
            "name": "Create webhook",
            "description": {},
            "url": {
              "path": [
                "webhooks"
              ],
              "host": [
                "{{baseUrl}}"
              ],
              "query": [],
              "variable": []
            },
            "method": "POST",
            "auth": null
          },
          "response": [
            {
              "id": "2ffcce8c-9f44-45ed-9597-67eb9c7349ee",
              "name": "Webhook created",
              "originalRequest": {
                "url": {
                  "path": [
                    "webhooks"
                  ],
                  "host": [
                    "{{baseUrl}}"
                  ],
                  "query": [],
                  "variable": []
                },
                "header": [
                  {
                    "description": {
                      "content": "Added as a part of security scheme: bearer",
                      "type": "text/plain"
                    },
                    "key": "Authorization",
                    "value": "Bearer <token>"
                  }
                ],
                "method": "POST",
                "body": {}
              },
              "status": "OK",
              "code": 200,
              "header": [
                {
                  "key": "Content-Type",
                  "value": "text/plain"
                }
              ],
              "body": "",
              "cookie": [],
              "_postman_previewlanguage": "text"
            }
          ],
          "event": [],
          "protocolProfileBehavior": {
            "disableBodyPruning": true
          }
        },
        {
          "id": "3778f502-84dd-4fff-9ab1-a882aa679ec7",
          "name": "Get webhook",
          "request": {
            "name": "Get webhook",
            "description": {},
            "url": {
              "path": [
                "webhooks",
                ":id"
              ],
              "host": [
                "{{baseUrl}}"
              ],
              "query": [],
              "variable": [
                {
                  "disabled": false,
                  "type": "any",
                  "value": "<string>",
                  "key": "id",
                  "description": "(Required) "
                }
              ]
            },
            "method": "GET",
            "auth": null
          },
          "response": [
            {
              "id": "c2909aa4-7bb7-472c-a297-4c1a3dda2f06",
              "name": "Webhook",
              "originalRequest": {
                "url": {
                  "path": [
                    "webhooks",
                    ":id"
                  ],
                  "host": [
                    "{{baseUrl}}"
                  ],
                  "query": [],
                  "variable": [
                    {
                      "disabled": false,
                      "type": "any",
                      "value": "<string>",
                      "key": "id",
                      "description": "(Required) "
                    }
                  ]
                },
                "header": [
                  {
                    "description": {
                      "content": "Added as a part of security scheme: bearer",
                      "type": "text/plain"
                    },
                    "key": "Authorization",
                    "value": "Bearer <token>"
                  }
                ],
                "method": "GET",
                "body": {}
              },
              "status": "OK",
              "code": 200,
              "header": [
                {
                  "key": "Content-Type",
                  "value": "text/plain"
                }
              ],
              "body": "",
              "cookie": [],
              "_postman_previewlanguage": "text"
            }
          ],
          "event": [],
          "protocolProfileBehavior": {
            "disableBodyPruning": true
          }
        },
        {
          "id": "dcbf6579-5e32-4027-80c6-4fe6a1d14262",
          "name": "Update webhook",
          "request": {
            "name": "Update webhook",
            "description": {},
            "url": {
              "path": [
                "webhooks",
                ":id"
              ],
              "host": [
                "{{baseUrl}}"
              ],
              "query": [],
              "variable": [
                {
                  "disabled": false,
                  "type": "any",
                  "value": "<string>",
                  "key": "id",
                  "description": "(Required) "
                }
              ]
            },
            "method": "PATCH",
            "auth": null
          },
          "response": [
            {
              "id": "aa6563de-a6de-46ea-8ee4-c2d37ed8e6a3",
              "name": "Updated",
              "originalRequest": {
                "url": {
                  "path": [
                    "webhooks",
                    ":id"
                  ],
                  "host": [
                    "{{baseUrl}}"
                  ],
                  "query": [],
                  "variable": [
                    {
                      "disabled": false,
                      "type": "any",
                      "value": "<string>",
                      "key": "id",
                      "description": "(Required) "
                    }
                  ]
                },
                "header": [
                  {
                    "description": {
                      "content": "Added as a part of security scheme: bearer",
                      "type": "text/plain"
                    },
                    "key": "Authorization",
                    "value": "Bearer <token>"
                  }
                ],
                "method": "PATCH",
                "body": {}
              },
              "status": "OK",
              "code": 200,
              "header": [
                {
                  "key": "Content-Type",
                  "value": "text/plain"
                }
              ],
              "body": "",
              "cookie": [],
              "_postman_previewlanguage": "text"
            }
          ],
          "event": [],
          "protocolProfileBehavior": {
            "disableBodyPruning": true
          }
        },
        {
          "id": "9a477c42-b0b7-47cc-a03a-7d60fa18f259",
          "name": "Delete webhook",
          "request": {
            "name": "Delete webhook",
            "description": {},
            "url": {
              "path": [
                "webhooks",
                ":id"
              ],
              "host": [
                "{{baseUrl}}"
              ],
              "query": [],
              "variable": [
                {
                  "disabled": false,
                  "type": "any",
                  "value": "<string>",
                  "key": "id",
                  "description": "(Required) "
                }
              ]
            },
            "method": "DELETE",
            "auth": null
          },
          "response": [
            {
              "id": "7cd855ce-ef84-4332-a8c5-bb98578d6c95",
              "name": "Deleted",
              "originalRequest": {
                "url": {
                  "path": [
                    "webhooks",
                    ":id"
                  ],
                  "host": [
                    "{{baseUrl}}"
                  ],
                  "query": [],
                  "variable": [
                    {
                      "disabled": false,
                      "type": "any",
                      "value": "<string>",
                      "key": "id",
                      "description": "(Required) "
                    }
                  ]
                },
                "header": [
                  {
                    "description": {
                      "content": "Added as a part of security scheme: bearer",
                      "type": "text/plain"
                    },
                    "key": "Authorization",
                    "value": "Bearer <token>"
                  }
                ],
                "method": "DELETE",
                "body": {}
              },
              "status": "No Content",
              "code": 204,
              "header": [
                {
                  "key": "Content-Type",
                  "value": "text/plain"
                }
              ],
              "body": "",
              "cookie": [],
              "_postman_previewlanguage": "text"
            }
          ],
          "event": [],
          "protocolProfileBehavior": {
            "disableBodyPruning": true
          }
        }
      ],
      "event": []
    },
    {
      "id": "86b5884e-ea1b-4421-8786-f191be8912e4",
      "name": "Subscriptions",
      "description": {
        "content": "",
        "type": "text/plain"
      },
      "item": [
        {
          "id": "6a07dea2-40b2-4382-9c9c-25bb69f0889c",
          "name": "Subscribe to call events",
          "request": {
            "name": "Subscribe to call events",
            "description": {},
            "url": {
              "path": [
                "webhook_call_event_subscription"
              ],
              "host": [
                "{{baseUrl}}"
              ],
              "query": [],
              "variable": []
            },
            "method": "POST",
            "auth": null
          },
          "response": [
            {
              "id": "c9ddaa66-8239-4290-a2b8-4412a0f340dc",
              "name": "Subscription created",
              "originalRequest": {
                "url": {
                  "path": [
                    "webhook_call_event_subscription"
                  ],
                  "host": [
                    "{{baseUrl}}"
                  ],
                  "query": [],
                  "variable": []
                },
                "header": [
                  {
                    "description": {
                      "content": "Added as a part of security scheme: bearer",
                      "type": "text/plain"
                    },
                    "key": "Authorization",
                    "value": "Bearer <token>"
                  }
                ],
                "method": "POST",
                "body": {}
              },
              "status": "OK",
              "code": 200,
              "header": [
                {
                  "key": "Content-Type",
                  "value": "text/plain"
                }
              ],
              "body": "",
              "cookie": [],
              "_postman_previewlanguage": "text"
            }
          ],
          "event": [],
          "protocolProfileBehavior": {
            "disableBodyPruning": true
          }
        },
        {
          "id": "ff92ff2a-3ba4-4d16-946c-dfdac3e4abde",
          "name": "Subscribe to SMS events",
          "request": {
            "name": "Subscribe to SMS events",
            "description": {},
            "url": {
              "path": [
                "webhook_sms_event_subscription"
              ],
              "host": [
                "{{baseUrl}}"
              ],
              "query": [],
              "variable": []
            },
            "method": "POST",
            "auth": null
          },
          "response": [
            {
              "id": "b1825e65-c44e-4a1c-8f15-ebbe67a309f1",
              "name": "Subscription created",
              "originalRequest": {
                "url": {
                  "path": [
                    "webhook_sms_event_subscription"
                  ],
                  "host": [
                    "{{baseUrl}}"
                  ],
                  "query": [],
                  "variable": []
                },
                "header": [
                  {
                    "description": {
                      "content": "Added as a part of security scheme: bearer",
                      "type": "text/plain"
                    },
                    "key": "Authorization",
                    "value": "Bearer <token>"
                  }
                ],
                "method": "POST",
                "body": {}
              },
              "status": "OK",
              "code": 200,
              "header": [
                {
                  "key": "Content-Type",
                  "value": "text/plain"
                }
              ],
              "body": "",
              "cookie": [],
              "_postman_previewlanguage": "text"
            }
          ],
          "event": [],
          "protocolProfileBehavior": {
            "disableBodyPruning": true
          }
        },
        {
          "id": "b32b8e77-6f28-4a87-a7d1-74622142d92f",
          "name": "Subscribe to contact events",
          "request": {
            "name": "Subscribe to contact events",
            "description": {},
            "url": {
              "path": [
                "webhook_contact_event_subscription"
              ],
              "host": [
                "{{baseUrl}}"
              ],
              "query": [],
              "variable": []
            },
            "method": "POST",
            "auth": null
          },
          "response": [
            {
              "id": "1c48110c-90b4-4ccb-967b-cdd81210325e",
              "name": "Subscription created",
              "originalRequest": {
                "url": {
                  "path": [
                    "webhook_contact_event_subscription"
                  ],
                  "host": [
                    "{{baseUrl}}"
                  ],
                  "query": [],
                  "variable": []
                },
                "header": [
                  {
                    "description": {
                      "content": "Added as a part of security scheme: bearer",
                      "type": "text/plain"
                    },
                    "key": "Authorization",
                    "value": "Bearer <token>"
                  }
                ],
                "method": "POST",
                "body": {}
              },
              "status": "OK",
              "code": 200,
              "header": [
                {
                  "key": "Content-Type",
                  "value": "text/plain"
                }
              ],
              "body": "",
              "cookie": [],
              "_postman_previewlanguage": "text"
            }
          ],
          "event": [],
          "protocolProfileBehavior": {
            "disableBodyPruning": true
          }
        }
      ],
      "event": []
    }
  ],
  "event": [],
  "variable": [
    {
      "type": "string",
      "value": "https://dialpad.com/api/v2",
      "key": "baseUrl"
    }
  ],
  "auth": {
    "type": "bearer",
    "bearer": [
      {
        "key": "token",
        "value": "{{bearerToken}}"
      }
    ]
  },
  "info": {
    "_postman_id": "c75d74e3-1ce7-42ea-a2ae-3a513e509939",
    "name": "Dialpad API",
    "schema": "https://schema.getpostman.com/json/collection/v2.1.0/collection.json",
    "description": {
      "content": "REST API for Dialpad's AI-powered cloud communications platform. Manage calls, users, offices, contacts, rooms, recordings, transcripts, webhooks and event subscriptions.",
      "type": "text/plain"
    }
  }
}